celar/__main__.py
celar/celar.tcss
celar-0.1.4.dist-info/licenses/LICENSE
celar-0.1.4.dist-info/METADATA
celar-0.1.4.dist-info/WHEEL
celar-0.1.4.dist-info/entry_points.txt
celar-0.1.4.dist-info/top_level.txt
celar-0.1.4.dist-info/RECORD
