Metadata-Version: 2.4
Name: celar
Version: 0.1.4
Summary: Simple CLI Social Media App
Author-email: simon0302010 <simon0302010@gmail.com>
License-Expression: GPL-3.0-only
Project-URL: Homepage, https://github.com/simon0302010/celar
Classifier: Operating System :: POSIX :: Linux
Classifier: Operating System :: Microsoft :: Windows
Requires-Python: <4.0,>=3.9
License-File: LICENSE
Requires-Dist: requests
Requires-Dist: questionary
Requires-Dist: textual
Requires-Dist: textual-image
Requires-Dist: textual-fspicker
Requires-Dist: Pillow
Dynamic: license-file
